setup.py
brynq_sdk_hr2day/__init__.py
brynq_sdk_hr2day/cost_center.py
brynq_sdk_hr2day/department.py
brynq_sdk_hr2day/department_details.py
brynq_sdk_hr2day/employee.py
brynq_sdk_hr2day/employer.py
brynq_sdk_hr2day/employment_conditions_cluster.py
brynq_sdk_hr2day/employment_relationship.py
brynq_sdk_hr2day/file.py
brynq_sdk_hr2day/hr2day.py
brynq_sdk_hr2day/job.py
brynq_sdk_hr2day/leave.py
brynq_sdk_hr2day/location.py
brynq_sdk_hr2day/payroll.py
brynq_sdk_hr2day/qualification.py
brynq_sdk_hr2day/sick_classification.py
brynq_sdk_hr2day/sick_leave.py
brynq_sdk_hr2day/sick_leave_period.py
brynq_sdk_hr2day/substitution.py
brynq_sdk_hr2day/wage_component_definition.py
brynq_sdk_hr2day/wage_component_output.py
brynq_sdk_hr2day/work_history.py
brynq_sdk_hr2day.egg-info/PKG-INFO
brynq_sdk_hr2day.egg-info/SOURCES.txt
brynq_sdk_hr2day.egg-info/dependency_links.txt
brynq_sdk_hr2day.egg-info/not-zip-safe
brynq_sdk_hr2day.egg-info/requires.txt
brynq_sdk_hr2day.egg-info/top_level.txt
brynq_sdk_hr2day/schemas/__init__.py
brynq_sdk_hr2day/schemas/cost_center.py
brynq_sdk_hr2day/schemas/department.py
brynq_sdk_hr2day/schemas/department_details.py
brynq_sdk_hr2day/schemas/employee.py
brynq_sdk_hr2day/schemas/employer.py
brynq_sdk_hr2day/schemas/employment_conditions_cluster.py
brynq_sdk_hr2day/schemas/employment_relationship.py
brynq_sdk_hr2day/schemas/file.py
brynq_sdk_hr2day/schemas/job.py
brynq_sdk_hr2day/schemas/leave.py
brynq_sdk_hr2day/schemas/leave_entitlement.py
brynq_sdk_hr2day/schemas/location.py
brynq_sdk_hr2day/schemas/payroll.py
brynq_sdk_hr2day/schemas/qualification.py
brynq_sdk_hr2day/schemas/sick_classification.py
brynq_sdk_hr2day/schemas/sick_leave.py
brynq_sdk_hr2day/schemas/sick_leave_period.py
brynq_sdk_hr2day/schemas/substitution.py
brynq_sdk_hr2day/schemas/wage_component_definition.py
brynq_sdk_hr2day/schemas/wage_component_output.py
brynq_sdk_hr2day/schemas/work_history.py