Metadata-Version: 1.0
Name: brynq-sdk-hr2day
Version: 1.0.2
Summary: BrynQ SDK for the HR2Day platform
Home-page: UNKNOWN
Author: BrynQ
Author-email: support@brynq.com
License: BrynQ License
Platform: UNKNOWN
